Workbook

Sheet Source
A1: VERIFIED SOURCE DATA — Dangote Refinery IPO Prospectus (7 Sept 2026, SEC-registered)
A2: Every figure below was read directly from the prospectus. Page references included. Do not edit this tab.
A4: Item | B4: Value | C4: Unit | D4: Source
A5: Shares in issue pre-offer | B5: 120128915901 | C5: shares | D5: Prospectus p.33 & p.62 (post private placement)
A6: IPO offer shares (base) | B6: 4100000000 | C6: shares | D6: Prospectus p.34
A7: Greenshoe / oversubscription cap | B7: 0.3 | C7: fraction | D7: Prospectus p.37 item 24 — 'up to 30% subject to SEC approval'
A8: Offer price | B8: 525 | C8: NGN/share | D8: Prospectus p.34
A9: Minimum subscription lot | B9: 10 | C9: shares | D9: Prospectus p.37 item 22
A10: Indicative market cap at listing | B10: 65220180848025 | C10: NGN | D10: Prospectus p.35 item 17
A11: Nameplate capacity (rerated) | B11: 700000 | C11: bpd | D11: Prospectus p.16 & p.108 (design 650,000; rerated after June 2026 tests)
A12: Litres per barrel | B12: 158.987 | C12: L | D12: Standard industry conversion (42 US gal)
A13: H1 2026 period length | B13: 181 | C13: days | D13: 1 Jan – 30 Jun 2026
A14: H1 2026 revenue | B14: 13909531000 | C14: USD | D14: Prospectus p.76 (audited, Deloitte)
A15: H1 2026 profit after tax | B15: 1820514000 | C15: USD | D15: Prospectus p.76 (audited, Deloitte)
A16: H1 2026 closing FX rate | B16: 1377 | C16: NGN/USD | D16: Prospectus p.17
... A27: Expansion added capacity | B27: 700000 | C27: bpd | D27: Prospectus p.34 (target 2029)
A29: NOTE 1: Media reported H1 revenue as $14.4bn; the audited prospectus figure is $13.91bn. Prospectus wins.
A30: NOTE 2: Internal discrepancy — KPMG extract (p.70) shows N'revenue 19,153,842m vs Historical Financial Info (p.76) 19,134,942m (~0.1%). USD figures agree. All outputs presented in USD.

Sheet Ownership
A1: WHAT DOES A SHARE ACTUALLY OWN? — physical refinery units
A3: Post-offer shares (base offer) | B3: =Source!B5+Source!B6
A4: Post-offer shares (greenshoe fully exercised) | B4: =Source!B5+Source!B6*(1+Source!B7)
A5: Barrels per day per share (base) | B5: =Source!B11/B4
A6: Millilitres of crude per share, per day | B6: =B6*Source!B12*1000
A7: Millilitres per minimum lot (10 shares), per day | B7: =B7*Source!B9
A8: Teaspoons per minimum lot, per day (1 tsp = 5 mL) | B8: =B8/5
A9: % of the entire refinery per minimum lot | B9: =Source!B9/B4*100
A12: YOUR DAILY 9 mL, SPLIT BY THE REFINERY'S ACTUAL PRODUCT YIELDS (p.111)
A13: Product | B13: Yield (actual) | C13: mL/day (per 10-share lot) | D13: Litres/year (per 10-share lot)
A14: PMS (petrol) | B14: =Source!B16 | C14: =$B$8*B14 | D14: =C14*365/1000
A15: AGO (diesel) | B15: =Source!B17 | C15: =$B$8*B15 | D15: =C15*365/1000
A16: ATF (jet fuel) | B16: =Source!B18 | C16: =$B$8*B16 | D16: =C16*365/1000
A17: RCO + CBFS | B17: =Source!B19 | C17: =$B$8*B17 | D17: =C17*365/1000
A18: LPG | B18: =Source!B20 | C18: =$B$8*B18 | D18: =C18*365/1000
A19: Polypropylene | B19: =Source!B21 | C19: =$B$8*B19 | D19: =C19*365/1000
A20: Total | C20: =SUM(C14:C19) | D20: =SUM(D14:D19)

Sheet Finance
A1: THE MONEY LAYER — what your ₦5,250 earns (H1 2026 audited, annualized as a stated assumption)
A3: H1 2026 daily revenue (USD) | B3: =Source!B13/Source!B14
A4: H1 2026 daily profit after tax (USD) | B4: =Source!B15/Source!B14
A5: Annualized revenue per 10-share lot (USD) | B5: =B3/Ownership!B4*Source!B9*365
A6: Annualized profit per 10-share lot (USD) | B6: =B4/Ownership!B4*Source!B9*365
A7: Annualized profit per 10-share lot (NGN @ 1,377) | B7: =B6*Source!B16
A8: Simple payback if 100% of profit paid out (years) | B8: =Source!B9*Source!B8/B7
A9: Annualized PAT, whole company (USD) | B9: =Source!B15*2
A10: Market cap at listing (USD @ 1,377) | B10: =Source!B10/Source!B16
A11: IMPLIED P/E (market cap ÷ annualized PAT) | B11: =B9/B8
A12: Hypothetical 100% dividend per 10-share lot | B12: =B6
A13: ...which would be paid in US DOLLARS | B13: (per prospectus dividend policy, pp.129-133 — user-verified)
A14: Gross refining margin per 10-share lot, per year (USD) | B14: =Ownership!B6*Source!B9*365*Source!B22
A15: Capex per bpd — original build | B15: =Source!B23/Source!B24
A16: ⚠ Annualizing H1 is an arithmetic exercise, NOT a forecast. Refining margins fluctuate with crude and product prices. | B16: =Source!B25/Source!B26

Sheet Limitations
A1: LIMITATIONS & HONEST CAVEATS — publish these alongside the results
A3: 1. Per-share throughput assumes steady-state at the rerated 700,000 bpd nameplate. Actual throughput varies with maintenance, crude mix and market conditions.
A4: 2. The greenshoe (up to 30% more shares, p.37) would dilute per-share figures by ~1%. Base-offer numbers used; full-exercise numbers shown on Ownership tab.
A5: 3. Annualizing H1 2026 (×2) assumes the second half performs identically. It is an assumption, not management guidance. Refining is cyclical.
A6: 4. Product yields are the actual 12-month figures to 30 June 2026 (p.111) — but yields shift with crude slate and operating mode.
A7: 5. Internal prospectus discrepancy: p.70 vs p.76 Naira revenue/PAT differ by ~0.1%; USD figures agree, so USD is used throughout.
A8: 6. Media reported H1 revenue of $14.4bn; the audited prospectus says $13.91bn. The prospectus figure is used.
A9: 7. GRM of $24.2/bbl is the Issuer's own 2026 estimate (p.80), not an audited actual and not guaranteed.
A10: 8. Market cap is the indicative listing valuation, not a market-tested price.
A11: 9. Dividend amount/timing is not guaranteed; the policy states payment in USD (pp.129-133) but payout ratio is not assumed here.
A12: 10. This is an educational analysis of public documents. It is NOT investment advice.
A13: Sources: Dangote Petroleum Refinery & Petrochemicals FZE — IPO Prospectus, 7 September 2026 (SEC-registered). All page references above.
